pytest_xdist_lock/__init__.py
pytest_xdist_lock/plugin.py
pytest_xdist_lock/py.typed
pytest_xdist_lock/locks/__init__.py
pytest_xdist_lock/locks/base_lock.py
pytest_xdist_lock/locks/file_lock.py
pytest_xdist_lock/locks/redis_lock.py
pytest_xdist_lock-0.1.4.dist-info/licenses/LICENSE
tests/__init__.py
tests/conftest.py
tests/test_basic.py
tests/test_concurrency.py
tests/test_context.py
tests/test_file_lock.py
tests/test_groups.py
tests/test_integration.py
tests/test_redis_lock.py
pytest_xdist_lock-0.1.4.dist-info/METADATA
pytest_xdist_lock-0.1.4.dist-info/WHEEL
pytest_xdist_lock-0.1.4.dist-info/entry_points.txt
pytest_xdist_lock-0.1.4.dist-info/top_level.txt
pytest_xdist_lock-0.1.4.dist-info/RECORD
