Metadata-Version: 2.4
Name: pytest-xdist-lock
Version: 0.1.4
Summary: Extension for pytest-xdist adding test and resource group locks for local and distributed runs
Author-email: KrzysztofRybczynski <rybczynski.k@gmail.com>
License: MIT
Project-URL: Homepage, https://github.com/KrzysztofRybczynski/pytest-xdist-lock
Project-URL: Repository, https://github.com/KrzysztofRybczynski/pytest-xdist-lock
Project-URL: Issues, https://github.com/KrzysztofRybczynski/pytest-xdist-lock/issues
Classifier: Programming Language :: Python :: 3.9
Classifier: Programming Language :: Python :: 3.10
Classifier: Programming Language :: Python :: 3.11
Classifier: Programming Language :: Python :: 3.12
Classifier: Framework :: Pytest
Classifier: Operating System :: OS Independent
Requires-Python: >=3.9
License-File: LICENSE
Requires-Dist: pytest>=6.0
Requires-Dist: pytest-xdist>=2.0
Requires-Dist: redis>=4.0
Dynamic: license-file
